cdktg/__init__.py
cdktg/py.typed
cdktg/_jsii/__init__.py
cdktg/_jsii/cdktg@0.0.40.jsii.tgz
cdktg/plus/__init__.py
cdktg/plus_aws/__init__.py
cdktg-0.0.40.data/scripts/cdktg
cdktg-0.0.40.dist-info/LICENSE
cdktg-0.0.40.dist-info/METADATA
cdktg-0.0.40.dist-info/WHEEL
cdktg-0.0.40.dist-info/top_level.txt
cdktg-0.0.40.dist-info/RECORD
